JiandanCubaoTensorflow20/README.md
JiandanCubaoTensorflow20/__init__.py
JiandanCubaoTensorflow20/__main__.py
JiandanCubaoTensorflow20/file.epub
JiandanCubaoTensorflow20/index.html
JiandanCubaoTensorflow20/css/__init__.py
JiandanCubaoTensorflow20/css/annotations.css
JiandanCubaoTensorflow20/css/main.css
JiandanCubaoTensorflow20/css/normalize.css
JiandanCubaoTensorflow20/css/popup.css
JiandanCubaoTensorflow20/font/__init__.py
JiandanCubaoTensorflow20/font/fontello.eot
JiandanCubaoTensorflow20/font/fontello.svg
JiandanCubaoTensorflow20/font/fontello.ttf
JiandanCubaoTensorflow20/font/fontello.woff
JiandanCubaoTensorflow20/img/__init__.py
JiandanCubaoTensorflow20/img/annotator-glyph-sprite.png
JiandanCubaoTensorflow20/img/annotator-icon-sprite.png
JiandanCubaoTensorflow20/img/apple-touch-icon.png
JiandanCubaoTensorflow20/img/cancelfullscreen.png
JiandanCubaoTensorflow20/img/close.png
JiandanCubaoTensorflow20/img/fullscreen.png
JiandanCubaoTensorflow20/img/loader.gif
JiandanCubaoTensorflow20/img/menu-icon.png
JiandanCubaoTensorflow20/img/save.png
JiandanCubaoTensorflow20/img/saved.png
JiandanCubaoTensorflow20/img/settings-s.png
JiandanCubaoTensorflow20/img/settings.png
JiandanCubaoTensorflow20/img/star.png
JiandanCubaoTensorflow20/js/__init__.py
JiandanCubaoTensorflow20/js/epub.js
JiandanCubaoTensorflow20/js/epub.min.js
JiandanCubaoTensorflow20/js/epub.min.map
JiandanCubaoTensorflow20/js/hooks.min.js
JiandanCubaoTensorflow20/js/hooks.min.map
JiandanCubaoTensorflow20/js/reader.js
JiandanCubaoTensorflow20/js/reader.js.map
JiandanCubaoTensorflow20/js/reader.min.js
JiandanCubaoTensorflow20/js/reader.min.map
JiandanCubaoTensorflow20/js/hooks/__init__.py
JiandanCubaoTensorflow20/js/hooks/extensions/__init__.py
JiandanCubaoTensorflow20/js/hooks/extensions/highlight.js
JiandanCubaoTensorflow20/js/libs/__init__.py
JiandanCubaoTensorflow20/js/libs/jquery.min.js
JiandanCubaoTensorflow20/js/libs/localforage.min.js
JiandanCubaoTensorflow20/js/libs/screenfull.js
jiandan_cubao_tensorflow_2_0-2024.3.4.0.dist-info/METADATA
jiandan_cubao_tensorflow_2_0-2024.3.4.0.dist-info/WHEEL
jiandan_cubao_tensorflow_2_0-2024.3.4.0.dist-info/entry_points.txt
jiandan_cubao_tensorflow_2_0-2024.3.4.0.dist-info/top_level.txt
jiandan_cubao_tensorflow_2_0-2024.3.4.0.dist-info/RECORD
